dm_control2gym/__init__.py
dm_control2gym/base_wrappers.py
dm_control2gym/recorder.py
dm_control2gym/util.py
dm_control2gym/viewer.py
dm_control2gym/wrapper.py
dm_control2gym-0.0.2.dist-info/LICENSE
dm_control2gym-0.0.2.dist-info/METADATA
dm_control2gym-0.0.2.dist-info/WHEEL
dm_control2gym-0.0.2.dist-info/top_level.txt
dm_control2gym-0.0.2.dist-info/RECORD
