Metadata-Version: 2.1
Name: dm-control2gym
Version: 0.0.2
Summary: dm_control suite for OpenAI Gym env
Home-page: https://github.com/Rowing0914/dm_control2gym
Author: Norio Kosaka
Author-email: kosakaboat@gmail.com
License: UNKNOWN
Platform: UNKNOWN
Classifier: Programming Language :: Python :: 3
Classifier: Programming Language :: Python :: 2
Classifier: License :: OSI Approved :: MIT License
Classifier: Operating System :: OS Independent
